esppy/__init__.py
esppy/algorithm.py
esppy/base.py
esppy/config.py
esppy/connection.py
esppy/connectorinfo.py
esppy/contquery.py
esppy/evtgen.py
esppy/exceptions.py
esppy/logger.py
esppy/mas.py
esppy/masStores.py
esppy/metadata.py
esppy/plotting.py
esppy/project.py
esppy/router.py
esppy/schema.py
esppy/transformers.py
esppy/websocket.py
esppy/ws4py.py
esppy/wsclient.py
esppy/connectors/__init__.py
esppy/connectors/adapter.py
esppy/connectors/bacnet.py
esppy/connectors/base.py
esppy/connectors/database.py
esppy/connectors/fs.py
esppy/connectors/kafka.py
esppy/connectors/modbus.py
esppy/connectors/mqtt.py
esppy/connectors/nurego.py
esppy/connectors/opcua.py
esppy/connectors/pi.py
esppy/connectors/project.py
esppy/connectors/pylon.py
esppy/connectors/rabbitmq.py
esppy/connectors/smtp.py
esppy/connectors/sniffer.py
esppy/connectors/solace.py
esppy/connectors/teradata.py
esppy/connectors/tervela.py
esppy/connectors/tibco.py
esppy/connectors/timer.py
esppy/connectors/url.py
esppy/connectors/uvc.py
esppy/connectors/websocket.py
esppy/connectors/websphere.py
esppy/espapi/__init__.py
esppy/espapi/api.py
esppy/espapi/codec.py
esppy/espapi/colors.py
esppy/espapi/connections.py
esppy/espapi/eventsources.py
esppy/espapi/k8s.py
esppy/espapi/tools.py
esppy/espapi/viewers.py
esppy/espapi/visuals.py
esppy/templates/__init__.py
esppy/templates/template.py
esppy/templates/xmls/KeypointsDetection.xml
esppy/templates/xmls/Logistic.xml
esppy/templates/xmls/ObjectDetection.xml
esppy/templates/xmls/ScoreTextConcept.xml
esppy/templates/xmls/SpeechToText.xml
esppy/templates/xmls/TextEmbedding.xml
esppy/tests/__init__.py
esppy/tests/test_algorithm.py
esppy/tests/test_config.py
esppy/tests/test_connection.py
esppy/tests/test_connectors.py
esppy/tests/test_contquery.py
esppy/tests/test_data_utils.py
esppy/tests/test_event_utils.py
esppy/tests/test_evtgen.py
esppy/tests/test_keyword_utils.py
esppy/tests/test_logger.py
esppy/tests/test_metadata.py
esppy/tests/test_plotting.py
sas_esppy-7.1.16.dist-info/LICENSE
sas_esppy-7.1.16.dist-info/LICENSE.txt
sas_esppy-7.1.16.dist-info/METADATA
sas_esppy-7.1.16.dist-info/WHEEL
sas_esppy-7.1.16.dist-info/top_level.txt
sas_esppy-7.1.16.dist-info/RECORD
