Metadata-Version: 2.1
Name: sas-esppy
Version: 7.1.16
Summary: SAS Event Stream Processing Python Interface
Home-page: https://github.com/sassoftware/python-esppy/
Author: SAS
Author-email: Robert.Levey@sas.com
License: Apache 2.0
Platform: UNKNOWN
Classifier: Development Status :: 5 - Production/Stable
Classifier: Environment :: Console
Classifier: Intended Audience :: Science/Research
Classifier: Programming Language :: Python
Classifier: Programming Language :: Python :: 2
Classifier: Programming Language :: Python :: 3
Classifier: Programming Language :: Python :: 2.7
Classifier: Programming Language :: Python :: 3.4
Classifier: Programming Language :: Python :: 3.5
Classifier: Programming Language :: Python :: 3.6
Classifier: Programming Language :: Python :: 3.7
Classifier: Topic :: Scientific/Engineering
Requires-Dist: pandas (>=0.16.0)
Requires-Dist: pillow
Requires-Dist: six (>=1.9.0)
Requires-Dist: plotly
Requires-Dist: ipywidgets
Requires-Dist: requests
Requires-Dist: graphviz
Requires-Dist: rbtranslations
Requires-Dist: websocket-client
Requires-Dist: ws4py
